sccde/__init__.py
sccde/check.py
sccde/cli.py
sccde/errors.py
sccde/main.py
sccde/model.py
sccde/pack.py
sccde/paths.py
sccde/server.py
sccde/utils.py
sccde/resources/__init__.py
sccde/resources/sample_collector.py
sccde/resources/sample_collector_html.zip
sccde/resources/sample_collector_ui.json
sccde/resources/sample_emitter.py
sccde/resources/sample_emitter_html.zip
sccde/resources/sample_emitter_ui.json
sccde/resources/sample_serializer.py
sccde/synapse_fw/speedbeesynapse/component/base.py
speedbeesynapse_sccde-0.1.11.dist-info/METADATA
speedbeesynapse_sccde-0.1.11.dist-info/WHEEL
speedbeesynapse_sccde-0.1.11.dist-info/entry_points.txt
speedbeesynapse_sccde-0.1.11.dist-info/RECORD
