Metadata-Version: 2.4
Name: speedbeesynapse-sccde
Version: 0.1.11
Summary: This package provides some tools for developing custom components of SpeeDBee-Synapse.
Classifier: Environment :: Console
Classifier: Intended Audience :: Developers
Classifier: Programming Language :: Python :: 3
Requires-Python: >=3.10
Requires-Dist: click>=8.1.8
Requires-Dist: watchfiles>=0.24.0
